{
  "exportedAt": "2026-04-13T14:11:07.267Z",
  "database": "memomind",
  "collections": {
    "users": [
      {
        "_id": "69dcf972277d7b93c380aa80",
        "email": "demo@memomind.com",
        "password": "$2b$10$.dY9VQ3AS3sSf4eIZ.pcau3oNj1lB5ABnwJak6haYLNW9oMpKN2DC",
        "name": "Người dùng Demo",
        "createdAt": "2026-04-13T14:10:58.654Z",
        "updatedAt": "2026-04-13T14:10:58.654Z",
        "__v": 0
      }
    ],
    "decks": [
      {
        "_id": "69dcf972277d7b93c380aa81",
        "userId": "69dcf972277d7b93c380aa80",
        "name": "Tiếng Anh TOEIC",
        "description": "Từ vựng TOEIC thường gặp",
        "cardCount": 10,
        "createdAt": "2026-04-13T14:10:58.711Z",
        "updatedAt": "2026-04-13T14:10:58.711Z",
        "__v": 0
      },
      {
        "_id": "69dcf972277d7b93c380aa8c",
        "userId": "69dcf972277d7b93c380aa80",
        "name": "Tiếng Nhật N5",
        "description": "Từ vựng cơ bản JLPT N5",
        "cardCount": 10,
        "createdAt": "2026-04-13T14:10:58.734Z",
        "updatedAt": "2026-04-13T14:10:58.734Z",
        "__v": 0
      },
      {
        "_id": "69dcf972277d7b93c380aa97",
        "userId": "69dcf972277d7b93c380aa80",
        "name": "Thuật ngữ Lập trình",
        "description": "Các thuật ngữ IT phổ biến",
        "cardCount": 10,
        "createdAt": "2026-04-13T14:10:58.740Z",
        "updatedAt": "2026-04-13T14:10:58.740Z",
        "__v": 0
      },
      {
        "_id": "69dcf972277d7b93c380aaa2",
        "userId": "69dcf972277d7b93c380aa80",
        "name": "Tiếng Anh Giao tiếp",
        "description": "Cụm từ giao tiếp hàng ngày",
        "cardCount": 10,
        "createdAt": "2026-04-13T14:10:58.745Z",
        "updatedAt": "2026-04-13T14:10:58.745Z",
        "__v": 0
      }
    ],
    "cards": [
      {
        "_id": "69dcf972277d7b93c380aa82",
        "deckId": "69dcf972277d7b93c380aa81",
        "userId": "69dcf972277d7b93c380aa80",
        "front": "accomplish",
        "back": "hoàn thành, đạt được",
        "easeFactor": 2.5,
        "interval": 0,
        "repetitions": 0,
        "lastReviewDate": null,
        "nextReviewDate": "2026-04-13T14:10:58.712Z",
        "createdAt": "2026-04-13T14:10:58.713Z",
        "updatedAt": "2026-04-13T14:10:58.713Z",
        "__v": 0
      },
      {
        "_id": "69dcf972277d7b93c380aa83",
        "deckId": "69dcf972277d7b93c380aa81",
        "userId": "69dcf972277d7b93c380aa80",
        "front": "negotiate",
        "back": "đàm phán, thương lượng",
        "easeFactor": 2.5,
        "interval": 0,
        "repetitions": 0,
        "lastReviewDate": null,
        "nextReviewDate": "2026-04-13T14:10:58.714Z",
        "createdAt": "2026-04-13T14:10:58.714Z",
        "updatedAt": "2026-04-13T14:10:58.714Z",
        "__v": 0
      },
      {
        "_id": "69dcf972277d7b93c380aa84",
        "deckId": "69dcf972277d7b93c380aa81",
        "userId": "69dcf972277d7b93c380aa80",
        "front": "deadline",
        "back": "hạn chót, thời hạn",
        "easeFactor": 2.5,
        "interval": 0,
        "repetitions": 0,
        "lastReviewDate": null,
        "nextReviewDate": "2026-04-13T14:10:58.716Z",
        "createdAt": "2026-04-13T14:10:58.716Z",
        "updatedAt": "2026-04-13T14:10:58.716Z",
        "__v": 0
      },
      {
        "_id": "69dcf972277d7b93c380aa85",
        "deckId": "69dcf972277d7b93c380aa81",
        "userId": "69dcf972277d7b93c380aa80",
        "front": "budget",
        "back": "ngân sách",
        "easeFactor": 2.5,
        "interval": 0,
        "repetitions": 0,
        "lastReviewDate": null,
        "nextReviewDate": "2026-04-13T14:10:58.716Z",
        "createdAt": "2026-04-13T14:10:58.717Z",
        "updatedAt": "2026-04-13T14:10:58.717Z",
        "__v": 0
      },
      {
        "_id": "69dcf972277d7b93c380aa86",
        "deckId": "69dcf972277d7b93c380aa81",
        "userId": "69dcf972277d7b93c380aa80",
        "front": "revenue",
        "back": "doanh thu",
        "easeFactor": 2.5,
        "interval": 0,
        "repetitions": 0,
        "lastReviewDate": null,
        "nextReviewDate": "2026-04-13T14:10:58.730Z",
        "createdAt": "2026-04-13T14:10:58.730Z",
        "updatedAt": "2026-04-13T14:10:58.730Z",
        "__v": 0
      },
      {
        "_id": "69dcf972277d7b93c380aa87",
        "deckId": "69dcf972277d7b93c380aa81",
        "userId": "69dcf972277d7b93c380aa80",
        "front": "implement",
        "back": "thực hiện, triển khai",
        "easeFactor": 2.5,
        "interval": 0,
        "repetitions": 0,
        "lastReviewDate": null,
        "nextReviewDate": "2026-04-13T14:10:58.731Z",
        "createdAt": "2026-04-13T14:10:58.731Z",
        "updatedAt": "2026-04-13T14:10:58.731Z",
        "__v": 0
      },
      {
        "_id": "69dcf972277d7b93c380aa88",
        "deckId": "69dcf972277d7b93c380aa81",
        "userId": "69dcf972277d7b93c380aa80",
        "front": "collaborate",
        "back": "hợp tác, cộng tác",
        "easeFactor": 2.5,
        "interval": 0,
        "repetitions": 0,
        "lastReviewDate": null,
        "nextReviewDate": "2026-04-13T14:10:58.731Z",
        "createdAt": "2026-04-13T14:10:58.732Z",
        "updatedAt": "2026-04-13T14:10:58.732Z",
        "__v": 0
      },
      {
        "_id": "69dcf972277d7b93c380aa89",
        "deckId": "69dcf972277d7b93c380aa81",
        "userId": "69dcf972277d7b93c380aa80",
        "front": "perspective",
        "back": "quan điểm, góc nhìn",
        "easeFactor": 2.5,
        "interval": 0,
        "repetitions": 0,
        "lastReviewDate": null,
        "nextReviewDate": "2026-04-13T14:10:58.732Z",
        "createdAt": "2026-04-13T14:10:58.732Z",
        "updatedAt": "2026-04-13T14:10:58.732Z",
        "__v": 0
      },
      {
        "_id": "69dcf972277d7b93c380aa8a",
        "deckId": "69dcf972277d7b93c380aa81",
        "userId": "69dcf972277d7b93c380aa80",
        "front": "evaluation",
        "back": "đánh giá, thẩm định",
        "easeFactor": 2.5,
        "interval": 0,
        "repetitions": 0,
        "lastReviewDate": null,
        "nextReviewDate": "2026-04-13T14:10:58.733Z",
        "createdAt": "2026-04-13T14:10:58.733Z",
        "updatedAt": "2026-04-13T14:10:58.733Z",
        "__v": 0
      },
      {
        "_id": "69dcf972277d7b93c380aa8b",
        "deckId": "69dcf972277d7b93c380aa81",
        "userId": "69dcf972277d7b93c380aa80",
        "front": "strategy",
        "back": "chiến lược",
        "easeFactor": 2.5,
        "interval": 0,
        "repetitions": 0,
        "lastReviewDate": null,
        "nextReviewDate": "2026-04-13T14:10:58.733Z",
        "createdAt": "2026-04-13T14:10:58.733Z",
        "updatedAt": "2026-04-13T14:10:58.733Z",
        "__v": 0
      },
      {
        "_id": "69dcf972277d7b93c380aa8d",
        "deckId": "69dcf972277d7b93c380aa8c",
        "userId": "69dcf972277d7b93c380aa80",
        "front": "わたし (watashi)",
        "back": "tôi",
        "easeFactor": 2.5,
        "interval": 0,
        "repetitions": 0,
        "lastReviewDate": null,
        "nextReviewDate": "2026-04-13T14:10:58.735Z",
        "createdAt": "2026-04-13T14:10:58.735Z",
        "updatedAt": "2026-04-13T14:10:58.735Z",
        "__v": 0
      },
      {
        "_id": "69dcf972277d7b93c380aa8e",
        "deckId": "69dcf972277d7b93c380aa8c",
        "userId": "69dcf972277d7b93c380aa80",
        "front": "がくせい (gakusei)",
        "back": "học sinh, sinh viên",
        "easeFactor": 2.5,
        "interval": 0,
        "repetitions": 0,
        "lastReviewDate": null,
        "nextReviewDate": "2026-04-13T14:10:58.735Z",
        "createdAt": "2026-04-13T14:10:58.735Z",
        "updatedAt": "2026-04-13T14:10:58.735Z",
        "__v": 0
      },
      {
        "_id": "69dcf972277d7b93c380aa8f",
        "deckId": "69dcf972277d7b93c380aa8c",
        "userId": "69dcf972277d7b93c380aa80",
        "front": "せんせい (sensei)",
        "back": "giáo viên, thầy/cô",
        "easeFactor": 2.5,
        "interval": 0,
        "repetitions": 0,
        "lastReviewDate": null,
        "nextReviewDate": "2026-04-13T14:10:58.736Z",
        "createdAt": "2026-04-13T14:10:58.736Z",
        "updatedAt": "2026-04-13T14:10:58.736Z",
        "__v": 0
      },
      {
        "_id": "69dcf972277d7b93c380aa90",
        "deckId": "69dcf972277d7b93c380aa8c",
        "userId": "69dcf972277d7b93c380aa80",
        "front": "ともだち (tomodachi)",
        "back": "bạn bè",
        "easeFactor": 2.5,
        "interval": 0,
        "repetitions": 0,
        "lastReviewDate": null,
        "nextReviewDate": "2026-04-13T14:10:58.736Z",
        "createdAt": "2026-04-13T14:10:58.736Z",
        "updatedAt": "2026-04-13T14:10:58.736Z",
        "__v": 0
      },
      {
        "_id": "69dcf972277d7b93c380aa91",
        "deckId": "69dcf972277d7b93c380aa8c",
        "userId": "69dcf972277d7b93c380aa80",
        "front": "たべる (taberu)",
        "back": "ăn",
        "easeFactor": 2.5,
        "interval": 0,
        "repetitions": 0,
        "lastReviewDate": null,
        "nextReviewDate": "2026-04-13T14:10:58.736Z",
        "createdAt": "2026-04-13T14:10:58.737Z",
        "updatedAt": "2026-04-13T14:10:58.737Z",
        "__v": 0
      },
      {
        "_id": "69dcf972277d7b93c380aa92",
        "deckId": "69dcf972277d7b93c380aa8c",
        "userId": "69dcf972277d7b93c380aa80",
        "front": "のむ (nomu)",
        "back": "uống",
        "easeFactor": 2.5,
        "interval": 0,
        "repetitions": 0,
        "lastReviewDate": null,
        "nextReviewDate": "2026-04-13T14:10:58.737Z",
        "createdAt": "2026-04-13T14:10:58.737Z",
        "updatedAt": "2026-04-13T14:10:58.737Z",
        "__v": 0
      },
      {
        "_id": "69dcf972277d7b93c380aa93",
        "deckId": "69dcf972277d7b93c380aa8c",
        "userId": "69dcf972277d7b93c380aa80",
        "front": "いく (iku)",
        "back": "đi",
        "easeFactor": 2.5,
        "interval": 0,
        "repetitions": 0,
        "lastReviewDate": null,
        "nextReviewDate": "2026-04-13T14:10:58.737Z",
        "createdAt": "2026-04-13T14:10:58.737Z",
        "updatedAt": "2026-04-13T14:10:58.737Z",
        "__v": 0
      },
      {
        "_id": "69dcf972277d7b93c380aa94",
        "deckId": "69dcf972277d7b93c380aa8c",
        "userId": "69dcf972277d7b93c380aa80",
        "front": "くる (kuru)",
        "back": "đến",
        "easeFactor": 2.5,
        "interval": 0,
        "repetitions": 0,
        "lastReviewDate": null,
        "nextReviewDate": "2026-04-13T14:10:58.738Z",
        "createdAt": "2026-04-13T14:10:58.738Z",
        "updatedAt": "2026-04-13T14:10:58.738Z",
        "__v": 0
      },
      {
        "_id": "69dcf972277d7b93c380aa95",
        "deckId": "69dcf972277d7b93c380aa8c",
        "userId": "69dcf972277d7b93c380aa80",
        "front": "おはよう (ohayou)",
        "back": "chào buổi sáng",
        "easeFactor": 2.5,
        "interval": 0,
        "repetitions": 0,
        "lastReviewDate": null,
        "nextReviewDate": "2026-04-13T14:10:58.739Z",
        "createdAt": "2026-04-13T14:10:58.739Z",
        "updatedAt": "2026-04-13T14:10:58.739Z",
        "__v": 0
      },
      {
        "_id": "69dcf972277d7b93c380aa96",
        "deckId": "69dcf972277d7b93c380aa8c",
        "userId": "69dcf972277d7b93c380aa80",
        "front": "ありがとう (arigatou)",
        "back": "cảm ơn",
        "easeFactor": 2.5,
        "interval": 0,
        "repetitions": 0,
        "lastReviewDate": null,
        "nextReviewDate": "2026-04-13T14:10:58.739Z",
        "createdAt": "2026-04-13T14:10:58.739Z",
        "updatedAt": "2026-04-13T14:10:58.739Z",
        "__v": 0
      },
      {
        "_id": "69dcf972277d7b93c380aa98",
        "deckId": "69dcf972277d7b93c380aa97",
        "userId": "69dcf972277d7b93c380aa80",
        "front": "API",
        "back": "Application Programming Interface - Giao diện lập trình ứng dụng",
        "easeFactor": 2.5,
        "interval": 0,
        "repetitions": 0,
        "lastReviewDate": null,
        "nextReviewDate": "2026-04-13T14:10:58.740Z",
        "createdAt": "2026-04-13T14:10:58.740Z",
        "updatedAt": "2026-04-13T14:10:58.740Z",
        "__v": 0
      },
      {
        "_id": "69dcf972277d7b93c380aa99",
        "deckId": "69dcf972277d7b93c380aa97",
        "userId": "69dcf972277d7b93c380aa80",
        "front": "REST",
        "back": "Representational State Transfer - Kiến trúc truyền tải dữ liệu qua HTTP",
        "easeFactor": 2.5,
        "interval": 0,
        "repetitions": 0,
        "lastReviewDate": null,
        "nextReviewDate": "2026-04-13T14:10:58.741Z",
        "createdAt": "2026-04-13T14:10:58.741Z",
        "updatedAt": "2026-04-13T14:10:58.741Z",
        "__v": 0
      },
      {
        "_id": "69dcf972277d7b93c380aa9a",
        "deckId": "69dcf972277d7b93c380aa97",
        "userId": "69dcf972277d7b93c380aa80",
        "front": "ORM",
        "back": "Object-Relational Mapping - Ánh xạ đối tượng sang cơ sở dữ liệu",
        "easeFactor": 2.5,
        "interval": 0,
        "repetitions": 0,
        "lastReviewDate": null,
        "nextReviewDate": "2026-04-13T14:10:58.741Z",
        "createdAt": "2026-04-13T14:10:58.741Z",
        "updatedAt": "2026-04-13T14:10:58.741Z",
        "__v": 0
      },
      {
        "_id": "69dcf972277d7b93c380aa9b",
        "deckId": "69dcf972277d7b93c380aa97",
        "userId": "69dcf972277d7b93c380aa80",
        "front": "JWT",
        "back": "JSON Web Token - Mã xác thực dạng JSON",
        "easeFactor": 2.5,
        "interval": 0,
        "repetitions": 0,
        "lastReviewDate": null,
        "nextReviewDate": "2026-04-13T14:10:58.742Z",
        "createdAt": "2026-04-13T14:10:58.742Z",
        "updatedAt": "2026-04-13T14:10:58.742Z",
        "__v": 0
      },
      {
        "_id": "69dcf972277d7b93c380aa9c",
        "deckId": "69dcf972277d7b93c380aa97",
        "userId": "69dcf972277d7b93c380aa80",
        "front": "CRUD",
        "back": "Create, Read, Update, Delete - Các thao tác cơ bản với dữ liệu",
        "easeFactor": 2.5,
        "interval": 0,
        "repetitions": 0,
        "lastReviewDate": null,
        "nextReviewDate": "2026-04-13T14:10:58.742Z",
        "createdAt": "2026-04-13T14:10:58.742Z",
        "updatedAt": "2026-04-13T14:10:58.742Z",
        "__v": 0
      },
      {
        "_id": "69dcf972277d7b93c380aa9d",
        "deckId": "69dcf972277d7b93c380aa97",
        "userId": "69dcf972277d7b93c380aa80",
        "front": "MVC",
        "back": "Model-View-Controller - Mô hình kiến trúc phần mềm",
        "easeFactor": 2.5,
        "interval": 0,
        "repetitions": 0,
        "lastReviewDate": null,
        "nextReviewDate": "2026-04-13T14:10:58.742Z",
        "createdAt": "2026-04-13T14:10:58.742Z",
        "updatedAt": "2026-04-13T14:10:58.742Z",
        "__v": 0
      },
      {
        "_id": "69dcf972277d7b93c380aa9e",
        "deckId": "69dcf972277d7b93c380aa97",
        "userId": "69dcf972277d7b93c380aa80",
        "front": "CI/CD",
        "back": "Continuous Integration/Deployment - Tích hợp và triển khai liên tục",
        "easeFactor": 2.5,
        "interval": 0,
        "repetitions": 0,
        "lastReviewDate": null,
        "nextReviewDate": "2026-04-13T14:10:58.743Z",
        "createdAt": "2026-04-13T14:10:58.743Z",
        "updatedAt": "2026-04-13T14:10:58.743Z",
        "__v": 0
      },
      {
        "_id": "69dcf972277d7b93c380aa9f",
        "deckId": "69dcf972277d7b93c380aa97",
        "userId": "69dcf972277d7b93c380aa80",
        "front": "SDK",
        "back": "Software Development Kit - Bộ công cụ phát triển phần mềm",
        "easeFactor": 2.5,
        "interval": 0,
        "repetitions": 0,
        "lastReviewDate": null,
        "nextReviewDate": "2026-04-13T14:10:58.743Z",
        "createdAt": "2026-04-13T14:10:58.743Z",
        "updatedAt": "2026-04-13T14:10:58.743Z",
        "__v": 0
      },
      {
        "_id": "69dcf972277d7b93c380aaa0",
        "deckId": "69dcf972277d7b93c380aa97",
        "userId": "69dcf972277d7b93c380aa80",
        "front": "Middleware",
        "back": "Phần mềm trung gian xử lý request giữa client và server",
        "easeFactor": 2.5,
        "interval": 0,
        "repetitions": 0,
        "lastReviewDate": null,
        "nextReviewDate": "2026-04-13T14:10:58.744Z",
        "createdAt": "2026-04-13T14:10:58.744Z",
        "updatedAt": "2026-04-13T14:10:58.744Z",
        "__v": 0
      },
      {
        "_id": "69dcf972277d7b93c380aaa1",
        "deckId": "69dcf972277d7b93c380aa97",
        "userId": "69dcf972277d7b93c380aa80",
        "front": "Repository Pattern",
        "back": "Mẫu thiết kế tách biệt logic truy cập dữ liệu khỏi business logic",
        "easeFactor": 2.5,
        "interval": 0,
        "repetitions": 0,
        "lastReviewDate": null,
        "nextReviewDate": "2026-04-13T14:10:58.745Z",
        "createdAt": "2026-04-13T14:10:58.745Z",
        "updatedAt": "2026-04-13T14:10:58.745Z",
        "__v": 0
      },
      {
        "_id": "69dcf972277d7b93c380aaa3",
        "deckId": "69dcf972277d7b93c380aaa2",
        "userId": "69dcf972277d7b93c380aa80",
        "front": "How are you doing?",
        "back": "Bạn khỏe không? (thân mật)",
        "easeFactor": 2.5,
        "interval": 0,
        "repetitions": 0,
        "lastReviewDate": null,
        "nextReviewDate": "2026-04-13T14:10:58.745Z",
        "createdAt": "2026-04-13T14:10:58.745Z",
        "updatedAt": "2026-04-13T14:10:58.745Z",
        "__v": 0
      },
      {
        "_id": "69dcf972277d7b93c380aaa4",
        "deckId": "69dcf972277d7b93c380aaa2",
        "userId": "69dcf972277d7b93c380aa80",
        "front": "Nice to meet you",
        "back": "Rất vui được gặp bạn",
        "easeFactor": 2.5,
        "interval": 0,
        "repetitions": 0,
        "lastReviewDate": null,
        "nextReviewDate": "2026-04-13T14:10:58.746Z",
        "createdAt": "2026-04-13T14:10:58.746Z",
        "updatedAt": "2026-04-13T14:10:58.746Z",
        "__v": 0
      },
      {
        "_id": "69dcf972277d7b93c380aaa5",
        "deckId": "69dcf972277d7b93c380aaa2",
        "userId": "69dcf972277d7b93c380aa80",
        "front": "Could you help me?",
        "back": "Bạn có thể giúp tôi không?",
        "easeFactor": 2.5,
        "interval": 0,
        "repetitions": 0,
        "lastReviewDate": null,
        "nextReviewDate": "2026-04-13T14:10:58.746Z",
        "createdAt": "2026-04-13T14:10:58.746Z",
        "updatedAt": "2026-04-13T14:10:58.746Z",
        "__v": 0
      },
      {
        "_id": "69dcf972277d7b93c380aaa6",
        "deckId": "69dcf972277d7b93c380aaa2",
        "userId": "69dcf972277d7b93c380aa80",
        "front": "I appreciate it",
        "back": "Tôi rất trân trọng điều đó",
        "easeFactor": 2.5,
        "interval": 0,
        "repetitions": 0,
        "lastReviewDate": null,
        "nextReviewDate": "2026-04-13T14:10:58.747Z",
        "createdAt": "2026-04-13T14:10:58.747Z",
        "updatedAt": "2026-04-13T14:10:58.747Z",
        "__v": 0
      },
      {
        "_id": "69dcf972277d7b93c380aaa7",
        "deckId": "69dcf972277d7b93c380aaa2",
        "userId": "69dcf972277d7b93c380aa80",
        "front": "Let me know",
        "back": "Hãy cho tôi biết nhé",
        "easeFactor": 2.5,
        "interval": 0,
        "repetitions": 0,
        "lastReviewDate": null,
        "nextReviewDate": "2026-04-13T14:10:58.747Z",
        "createdAt": "2026-04-13T14:10:58.747Z",
        "updatedAt": "2026-04-13T14:10:58.747Z",
        "__v": 0
      },
      {
        "_id": "69dcf972277d7b93c380aaa8",
        "deckId": "69dcf972277d7b93c380aaa2",
        "userId": "69dcf972277d7b93c380aa80",
        "front": "Take your time",
        "back": "Cứ từ từ, không vội",
        "easeFactor": 2.5,
        "interval": 0,
        "repetitions": 0,
        "lastReviewDate": null,
        "nextReviewDate": "2026-04-13T14:10:58.748Z",
        "createdAt": "2026-04-13T14:10:58.748Z",
        "updatedAt": "2026-04-13T14:10:58.748Z",
        "__v": 0
      },
      {
        "_id": "69dcf972277d7b93c380aaa9",
        "deckId": "69dcf972277d7b93c380aaa2",
        "userId": "69dcf972277d7b93c380aa80",
        "front": "It makes sense",
        "back": "Điều đó hợp lý",
        "easeFactor": 2.5,
        "interval": 0,
        "repetitions": 0,
        "lastReviewDate": null,
        "nextReviewDate": "2026-04-13T14:10:58.748Z",
        "createdAt": "2026-04-13T14:10:58.748Z",
        "updatedAt": "2026-04-13T14:10:58.748Z",
        "__v": 0
      },
      {
        "_id": "69dcf972277d7b93c380aaaa",
        "deckId": "69dcf972277d7b93c380aaa2",
        "userId": "69dcf972277d7b93c380aa80",
        "front": "I'm looking forward to it",
        "back": "Tôi rất mong chờ điều đó",
        "easeFactor": 2.5,
        "interval": 0,
        "repetitions": 0,
        "lastReviewDate": null,
        "nextReviewDate": "2026-04-13T14:10:58.748Z",
        "createdAt": "2026-04-13T14:10:58.748Z",
        "updatedAt": "2026-04-13T14:10:58.748Z",
        "__v": 0
      },
      {
        "_id": "69dcf972277d7b93c380aaab",
        "deckId": "69dcf972277d7b93c380aaa2",
        "userId": "69dcf972277d7b93c380aa80",
        "front": "No worries",
        "back": "Không sao đâu, đừng lo",
        "easeFactor": 2.5,
        "interval": 0,
        "repetitions": 0,
        "lastReviewDate": null,
        "nextReviewDate": "2026-04-13T14:10:58.749Z",
        "createdAt": "2026-04-13T14:10:58.749Z",
        "updatedAt": "2026-04-13T14:10:58.749Z",
        "__v": 0
      },
      {
        "_id": "69dcf972277d7b93c380aaac",
        "deckId": "69dcf972277d7b93c380aaa2",
        "userId": "69dcf972277d7b93c380aa80",
        "front": "Keep in touch",
        "back": "Giữ liên lạc nhé",
        "easeFactor": 2.5,
        "interval": 0,
        "repetitions": 0,
        "lastReviewDate": null,
        "nextReviewDate": "2026-04-13T14:10:58.749Z",
        "createdAt": "2026-04-13T14:10:58.749Z",
        "updatedAt": "2026-04-13T14:10:58.749Z",
        "__v": 0
      }
    ]
  },
  "stats": {
    "users": 1,
    "decks": 4,
    "cards": 40
  }
}